{
  "Version": "1.3",
  "ID": "f1josz5g67zbvwyus6qonjvxx3vphnfors5sbucvq",
  "Issue Number": "31",
  "Client Contract Address": "f410fs7htfzjairhb32g4kcfwckoghaxcdmlpkugjtca",
  "Client": {
    "Name": "",
    "Region": "",
    "Industry": "",
    "Website": "",
    "Social Media": "",
    "Social Media Type": "",
    "Role": ""
  },
  "Project": {
    "Brief history of your project and organization": "",
    "Is this project associated with other projects/ecosystem stakeholders?": "",
    "Describe the data being stored onto Filecoin": "",
    "Where was the data currently stored in this dataset sourced from": "",
    "How do you plan to prepare the dataset": "",
    "Please share a sample of the data (a link to a file, an image, a table, etc., are good ways to do this.)": "",
    "Confirm that this is a public dataset that can be retrieved by anyone on the network (i.e., no specific permissions or access rights are required to view the data)": "",
    "What is the expected retrieval frequency for this data": "",
    "For how long do you plan to keep this dataset stored on Filecoin": "",
    "In which geographies do you plan on making storage deals": "",
    "How will you be distributing your data to storage providers": "",
    "Please list the provider IDs and location of the storage providers you will be working with. Note that it is a requirement to list a minimum of 5 unique provider IDs, and that your client address will be verified against this list in the future": "",
    "Can you confirm that you will follow the Fil+ guideline (Data owner should engage at least 4 SPs and no single SP ID should receive >30% of a client's allocated DataCap)": ""
  },
  "Datacap": {
    "Type": "ldn-v3",
    "Data Type": "Slingshot",
    "Total Requested Amount": "1401TiB",
    "Single Size Dataset": "",
    "Replicas": 0,
    "Weekly Allocation": "5PiB"
  },
  "Lifecycle": {
    "State": "Granted",
    "Validated At": "2026-03-06 16:15:38.749213042 UTC",
    "Validated By": "vvkio",
    "Active": true,
    "Updated At": "2026-03-06 16:15:38.749208479 UTC",
    "Active Request ID": "49747281-6cd8-44df-a532-de411ec0c474",
    "On Chain Address": "f1josz5g67zbvwyus6qonjvxx3vphnfors5sbucvq",
    "Multisig Address": "false",
    "edited": false
  },
  "Allocation Requests": [
    {
      "ID": "49747281-6cd8-44df-a532-de411ec0c474",
      "Request Type": "First",
      "Created At": "2026-03-06 15:38:28.936838987 UTC",
      "Updated At": "2026-03-06 15:38:28.936840120 UTC",
      "Active": false,
      "Allocation Amount": "1125899906842624 B",
      "Amount of Datacap Sent to Contract": "1125899906842624 B",
      "Signers": [
        {
          "Github Username": "vvkio",
          "Signing Address": "f1zav5ykfacz4crj57crnbi55zp5733poswv6rxly",
          "Created At": "2026-03-06 16:15:36.982000000 UTC",
          "Message CID": "bafy2bzaceamezd6he5i2c2tfuwaer2u4gi6ztj4g4wr2qaqb7lgcnrhjb7mms",
          "Increase allowance CID": "bafy2bzacecxk4m37vtvs3tra4mq4l4ibvw4ykhc7z3hlv6z6cou3c4elydtwy"
        }
      ]
    }
  ]
}